flashlight_text.dylibs/libflashlight-text.0.0.4.dylib
flashlight_text.dylibs/libkenlm.dylib
flashlight/lib/text/libflashlight-text.0.0.4.dylib
flashlight/lib/text/version.py
flashlight/lib/text/flashlight_lib_text_decoder.cpython-310-darwin.so
flashlight/lib/text/__init__.py
flashlight/lib/text/libflashlight-text-kenlm.dylib
flashlight/lib/text/libflashlight-text.0.dylib
flashlight/lib/text/libflashlight-text.dylib
flashlight/lib/text/libflashlight-text-kenlm.0.0.4.dylib
flashlight/lib/text/flashlight_lib_text_decoder_kenlm.cpython-310-darwin.so
flashlight/lib/text/dictionary.py
flashlight/lib/text/flashlight_lib_text_dictionary.cpython-310-darwin.so
flashlight/lib/text/libflashlight-text-kenlm.0.dylib
flashlight/lib/text/decoder/__init__.py
flashlight/lib/text/decoder/kenlm.py
flashlight_text-0.0.7.dist-info/RECORD
flashlight_text-0.0.7.dist-info/LICENSE
flashlight_text-0.0.7.dist-info/WHEEL
flashlight_text-0.0.7.dist-info/top_level.txt
flashlight_text-0.0.7.dist-info/METADATA
