Metadata-Version: 2.1
Name: flashlight-text
Version: 0.0.7
Summary: Flashlight Text bindings for Python
Home-page: https://github.com/flashlight/text
Author: Jacob Kahn
Author-email: jacobkahn1@gmail.com
License: BSD licensed, as found in the LICENSE file
Classifier: Programming Language :: Python :: 3.6
Classifier: Programming Language :: Python :: 3.7
Classifier: Programming Language :: Python :: 3.8
Classifier: Programming Language :: Python :: 3.9
Classifier: Programming Language :: Python :: 3.10
Classifier: Programming Language :: Python :: 3.11
Classifier: Topic :: Scientific/Engineering :: Artificial Intelligence
Classifier: Operating System :: OS Independent
Requires-Python: >=3.6
License-File: LICENSE
